gptstonks/wrappers/__init__.py
gptstonks/wrappers/kernels/__init__.py
gptstonks/wrappers/kernels/auto_multistep_query_engine.py
gptstonks/wrappers/kernels/auto_rag.py
gptstonks/wrappers/kernels/mitheithel.py
gptstonks/wrappers/llms/__init__.py
gptstonks/wrappers/llms/chat_model_llm_iface.py
gptstonks/wrappers/retrievers/__init__.py
gptstonks/wrappers/retrievers/hybrid_or_retriever.py
gptstonks_wrappers-0.0.3.post1.dist-info/METADATA
gptstonks_wrappers-0.0.3.post1.dist-info/WHEEL
gptstonks_wrappers-0.0.3.post1.dist-info/entry_points.txt
gptstonks_wrappers-0.0.3.post1.dist-info/RECORD
