Metadata-Version: 2.1
Name: gptstonks-wrappers
Version: 0.0.3.post1
Summary: Useful wrappers around common AI tools: LangChain, LlamaIndex, etc.
Author-Email: GPTStonks Team <hello@gptstonks.net>
License: MIT
Classifier: Programming Language :: Python :: 3
Classifier: License :: OSI Approved :: MIT License
Classifier: Operating System :: OS Independent
Project-URL: Homepage, https://github.com/GPTStonks/gptstonks
Project-URL: Bug Tracker, https://github.com/GPTStonks/gptstonks/issues
Requires-Python: <3.12,>=3.10
Requires-Dist: rank-bm25>=0.2.2
Requires-Dist: llama-index>=0.10.13
Requires-Dist: langchain<0.4,>=0.3
Requires-Dist: llama-index-llms-openai>=0.1.6
Requires-Dist: llama-index-retrievers-bm25>=0.1.3
Requires-Dist: llama-index-readers-file>=0.1.33
Requires-Dist: langchain-community<0.4,>=0.3
Provides-Extra: huggingface
Requires-Dist: llama-index-embeddings-huggingface>=0.1.3; extra == "huggingface"
Requires-Dist: llama-index-llms-huggingface>=0.1.3; extra == "huggingface"
Provides-Extra: testing
Requires-Dist: pytest; extra == "testing"
Requires-Dist: pytest-cov; extra == "testing"
Requires-Dist: trio>=0.23.2; extra == "testing"
Requires-Dist: sentence-transformers>=2.2.2; extra == "testing"
Requires-Dist: pytest-asyncio>=0.23.5; extra == "testing"
Requires-Dist: duckduckgo-search>=4.5.0; extra == "testing"
Requires-Dist: wikipedia>=1.4.0; extra == "testing"
Requires-Dist: pinecone-client>=3.2.2; extra == "testing"
Requires-Dist: llama-index-vector-stores-pinecone>=0.1.6; extra == "testing"
